cobs_index.cpython-38-x86_64-linux-gnu.so
cobs.bin
.libscobs_index/libz-eb09ad1d.so.1.2.3
.libscobs_index/libgomp-f7e03b3e.so.1.0.0
.libscobs/libz-eb09ad1d.so.1.2.3
.libscobs/libgomp-f7e03b3e.so.1.0.0
cobs_index-0.1.2.data/scripts/cobs
cobs_index-0.1.2.dist-info/RECORD
cobs_index-0.1.2.dist-info/top_level.txt
cobs_index-0.1.2.dist-info/METADATA
cobs_index-0.1.2.dist-info/WHEEL
