Metadata-Version: 2.1
Name: cobs-index
Version: 0.1.2
Summary: Compact Bit-Sliced Signature Index (COBS)
Home-page: https://panthema.net/cobs
Author: Timo Bingmann
Author-email: tbdev@panthema.net
License: UNKNOWN
Platform: UNKNOWN
Classifier: Development Status :: 4 - Beta
Classifier: Topic :: Scientific/Engineering :: Bio-Informatics
Classifier: Topic :: Text Processing :: Indexing
